setup.py
window/__init__.py
window/window.py
window_maker.egg-info/PKG-INFO
window_maker.egg-info/SOURCES.txt
window_maker.egg-info/dependency_links.txt
window_maker.egg-info/top_level.txt