Metadata-Version: 2.1
Name: window-maker
Version: 0.0.1
Summary: a python module which you can easy make windows
Home-page: UNKNOWN
License: UNKNOWN
Platform: UNKNOWN
Requires: tkinter
